pixion/__init__.py
pixion/pixion.py
pixion-0.1.1.dist-info/METADATA
pixion-0.1.1.dist-info/WHEEL
pixion-0.1.1.dist-info/entry_points.txt
pixion-0.1.1.dist-info/licenses/LICENSE
pixion-0.1.1.dist-info/RECORD
