Metadata-Version: 2.4
Name: pixion
Version: 0.1.1
Summary: Tools and Library built at Pixel Perception
License: GNU General Public License v3
License-File: LICENSE
Keywords: python
Author: Saurabh Khanduja
Author-email: khandujasaurabh@gmail.com
Requires-Python: >=3.9
Classifier: Development Status :: 3 - Alpha
Classifier: Intended Audience :: Developers
Classifier: Intended Audience :: Science/Research
Classifier: License :: OSI Approved :: Apache Software License
Classifier: Operating System :: OS Independent
Classifier: Programming Language :: Python :: 3
Classifier: Programming Language :: Python :: 3.9
Classifier: Programming Language :: Python :: 3.10
Classifier: Programming Language :: Python :: 3.11
Classifier: Programming Language :: Python :: 3.12
Classifier: Programming Language :: Python :: 3.13
Classifier: Topic :: Scientific/Engineering :: Artificial Intelligence
Classifier: Topic :: Software Development :: Libraries :: Python Modules
Requires-Dist: numpy (>=1.26.0,<2.0.0)
Requires-Dist: opencv-python (>=4.10.0,<5.0.0)
Project-URL: Bug Tracker, https://github.com/saurabheights/pixion/issues
Project-URL: Documentation, https://python-poetry.org/docs/
Project-URL: Repository, https://github.com/saurabheights/pixion
